AUTHORS
ChangeLog
MANIFEST.in
README.rst
babel.cfg
requirements.txt
setup.cfg
setup.py
test-requirements.txt
tox.ini
doc/Makefile
doc/source/conf.py
doc/source/index.rst
doc/source/plcloud.rst
plcloudclient/__init__.py
plcloudclient/tests/__init__.py
plcloudclient/tests/v1_0/__init__.py
plcloudclient/tests/v1_0/test_cdn.py
plcloudclient/tests/v1_0/test_client.py
plcloudclient/tests/v1_0/test_ticket.py
plcloudclient/tests/v1_0/utils.py
plcloudclient/v1_0/__init__.py
plcloudclient/v1_0/cdn.py
plcloudclient/v1_0/client.py
plcloudclient/v1_0/shell.py
plcloudclient/v1_0/ticket.py
python_plcloudclient.egg-info/PKG-INFO
python_plcloudclient.egg-info/SOURCES.txt
python_plcloudclient.egg-info/dependency_links.txt
python_plcloudclient.egg-info/not-zip-safe
python_plcloudclient.egg-info/requires.txt
python_plcloudclient.egg-info/top_level.txt